.gitignore
.travis.yml
CHANGES
CONTRIBUTING.md
LICENSE
MANIFEST.in
README.md
README.rst
setup.py
behvpn/__init__.py
behvpn/asyncdns.py
behvpn/common.py
behvpn/encrypt.py
behvpn/eventloop.py
behvpn/local.py
behvpn/lru_cache.py
behvpn/server.py
behvpn/tcprelay.py
behvpn/udprelay.py
behvpn/utils.py
behvpn.egg-info/PKG-INFO
behvpn.egg-info/SOURCES.txt
behvpn.egg-info/dependency_links.txt
behvpn.egg-info/entry_points.txt
behvpn.egg-info/top_level.txt
behvpn/crypto/__init__.py
behvpn/crypto/ctypes_openssl.py
behvpn/crypto/m2.py
behvpn/crypto/rc4_md5.py
behvpn/crypto/salsa20_ctr.py
debian/changelog
debian/compat
debian/config.json
debian/control
debian/copyright
debian/docs
debian/init.d
debian/install
debian/rules
debian/shadowsocks.default
debian/shadowsocks.manpages
debian/sslocal.1
debian/ssserver.1
debian/source/format
tests/aes-cfb1.json
tests/aes-cfb8.json
tests/aes-ctr.json
tests/aes.json
tests/fastopen.json
tests/rc4-md5.json
tests/salsa20.json
tests/server-multi-passwd-client-side.json
tests/server-multi-passwd-table.json
tests/server-multi-passwd.json
tests/server-multi-ports.json
tests/table.json
tests/test.py
tests/test_latency.py
tests/workers.json
tests/socksify/install.sh
tests/socksify/socks.conf