Metadata-Version: 1.1
Name: behvpn
Version: 2.3.2
Summary: A fast tunnel proxy that help you get through firewalls
Home-page: https://github.com/cep-ter/behvpn
Author: 3epter
Author-email: sepehr.r201400@gmail.com
License: MIT
Platform: UNKNOWN
Classifier: License :: OSI Approved :: MIT License
Classifier: Programming Language :: Python :: 2
Classifier: Programming Language :: Python :: 2.6
Classifier: Programming Language :: Python :: 2.7
Classifier: Topic :: Internet :: Proxy Servers
